gtfs_aggregator_checker
