Metadata-Version: 2.1
Name: gtfs-aggregator-checker
Version: 1.0.0
Summary: Tool for checking if transit urls are on aggregator websites
Home-page: https://github.com/cal-itp/gtfs-aggregator-checker
Author: 
Author-email: 
License: UNKNOWN
Platform: UNKNOWN
